dsplayer_youtube/__init__.py
dsplayer_youtube/youtube.py
plugin/__init__.py
plugin/plugin.py
dsplayer_youtube-1.3.0.dist-info/LICENSE
dsplayer_youtube-1.3.0.dist-info/METADATA
dsplayer_youtube-1.3.0.dist-info/WHEEL
dsplayer_youtube-1.3.0.dist-info/entry_points.txt
dsplayer_youtube-1.3.0.dist-info/top_level.txt
dsplayer_youtube-1.3.0.dist-info/RECORD
